linen_closet-0.1.0.dist-info/METADATA
linen_closet-0.1.0.dist-info/WHEEL
linen_closet-0.1.0.dist-info/license_files/LICENSE
linen_closet/__init__.py
linen_closet/linen_closet.cpython-310-x86_64-linux-gnu.so
linen_closet-0.1.0.dist-info/RECORD
